AsyncTaskLib/__init__.py
USBMonitorUtilsLib/__init__.py
USBMonitorUtilsLib/attiributes.py
USBMonitorUtilsLib/usb_monitor.c
USBMonitorUtilsLib/usb_monitor.cpython-311-x86_64-linux-gnu.so
usb_monitor_utils_lib-0.3.3.dist-info/METADATA
usb_monitor_utils_lib-0.3.3.dist-info/WHEEL
usb_monitor_utils_lib-0.3.3.dist-info/top_level.txt
usb_monitor_utils_lib-0.3.3.dist-info/RECORD
