Metadata-Version: 2.1
Name: usb-monitor-utils-lib
Version: 0.3.3
Summary: A fast Cython-based package
Author-email: Ariakus Fordring <ariakusfrodringg@gmail.com>
Project-URL: Homepage, https://github.com/yourusername/my_cython_package
Keywords: cython,example
Classifier: Development Status :: 3 - Alpha
Classifier: Intended Audience :: Developers
Classifier: License :: OSI Approved :: MIT License
Classifier: Programming Language :: Python :: 3
Classifier: Programming Language :: C
Classifier: Operating System :: OS Independent
Requires-Python: >=3.11
Requires-Dist: cython
Requires-Dist: usb-monitor
